examples/__init__.py
examples/reverse_api_example.py
examples/scrape_forum.py
tests/__init__.py
tests/test_core.py
tests/test_disguise.py
tests/test_structure.py
webchameleon/__init__.py
webchameleon/api_reverse.py
webchameleon/core.py
webchameleon/disguise.py
webchameleon/exceptions.py
webchameleon/relations.py
webchameleon/storage.py
webchameleon/structure.py
webchameleon/configs/__init__.py
webchameleon/configs/settings.py
webchameleon/utils/__init__.py
webchameleon/utils/helpers.py
webchameleon/utils/logger.py
webchameleon/utils/timers.py
webchameleon_tool-1.3.0.dist-info/licenses/LICENSE
webchameleon_tool-1.3.0.dist-info/METADATA
webchameleon_tool-1.3.0.dist-info/WHEEL
webchameleon_tool-1.3.0.dist-info/top_level.txt
webchameleon_tool-1.3.0.dist-info/RECORD
