Metadata-Version: 2.4
Name: webchameleon-tool
Version: 1.3.0
Summary: A powerful web scraping and API reversal tool
Home-page: https://github.com/mrivky67/webchameleon
Author: Muhammad Rivky
Author-email: muhrivky67@gmail.com
Keywords: web scraping,api reversal,data extraction,automation
Classifier: Programming Language :: Python :: 3
Classifier: Programming Language :: Python :: 3.7
Classifier: Programming Language :: Python :: 3.8
Classifier: Programming Language :: Python :: 3.9
Classifier: Programming Language :: Python :: 3.10
Classifier: Programming Language :: Python :: 3.11
Classifier: Programming Language :: Python :: 3.12
Classifier: License :: OSI Approved :: MIT License
Classifier: Operating System :: OS Independent
Classifier: Intended Audience :: Developers
Classifier: Topic :: Software Development :: Libraries :: Python Modules
Requires-Python: >=3.7
License-File: LICENSE
Requires-Dist: requests>=2.25.1
Requires-Dist: beautifulsoup4>=4.9.3
Requires-Dist: networkx>=2.5
Requires-Dist: playwright>=1.30.0
Requires-Dist: aiohttp>=3.8.0
Requires-Dist: aiolimiter>=1.0.0
Requires-Dist: cachetools>=5.0.0
Requires-Dist: aiohttp-retry>=2.8.0
Requires-Dist: nltk>=3.6.5
Requires-Dist: python-louvain>=0.16
Requires-Dist: faker>=18.0.0
Requires-Dist: matplotlib>=3.5.0
Requires-Dist: numpy>=1.21.0
Requires-Dist: brotli>=1.1.0
Dynamic: author
Dynamic: author-email
Dynamic: classifier
Dynamic: description
Dynamic: description-content-type
Dynamic: home-page
Dynamic: keywords
Dynamic: license-file
Dynamic: requires-dist
Dynamic: requires-python
Dynamic: summary
